hw_1.v
module decoder(E , In , Out);
input E;
input [2:0] In;
output[7:0] Out;
wire [7:0]  Out;
assign Out  =E ? (8'b1 << In) : 8'h0;

endmodule

hw_1_tb.v
module decoder_3_8_tb;
reg       E_tb;
reg   [2:0]   In_tb;
wire  [7:0]   out_tb;
decoder decoder_1(.E(E_tb), .In(In_tb), .Out(Out_tb));


initial begin
  #0  E_tb = 0 ; In_tb = 3'b000;
  #10  E_tb = 1 ; In_tb = 3'b000;
  #10  E_tb = 1 ; In_tb = 3'b001;
  #10  E_tb = 1 ; In_tb = 3'b010;
  #10  E_tb = 1 ; In_tb = 3'b011;
  #10  E_tb = 1 ; In_tb = 3'b100;
  #10  E_tb = 1 ; In_tb = 3'b101;
  #10  E_tb = 1 ; In_tb = 3'b110;
  #10  E_tb = 1 ; In_tb = 3'b111;
  #10  $finish;
end
initial begin
    $dumpfile("decoder.vcd");
    $dumpvars(0, decoder_1);
    end
    endmodule

decoder.vcd
$date
	Tue Mar 22 19:07:45 2022
$end
$version
	Icarus Verilog
$end
$timescale
	1s
$end
$scope module decoder_3_8_tb $end
$scope module decoder_1 $end
$var wire 1 ! E $end
$var wire 3 " In [2:0] $end
$var wire 8 # Out [7:0] $end
$upscope $end
$upscope $end
$enddefinitions $end
#0
$dumpvars
b0 #
b0 "
0!
$end
#10
b1 #
1!
#20
b10 #
b1 "
#30
b100 #
b10 "
#40
b1000 #
b11 "
#50
b10000 #
b100 "
#60
b100000 #
b101 "
#70
b1000000 #
b110 "
#80
b10000000 #
b111 "
